pmenu_lib/__init__.py
pmenu_lib/cli.py
pmenu_lib/pmenu.py
pmenu_lib-1.2.2.dist-info/licenses/LICENSE
pmenu_lib-1.2.2.dist-info/METADATA
pmenu_lib-1.2.2.dist-info/WHEEL
pmenu_lib-1.2.2.dist-info/entry_points.txt
pmenu_lib-1.2.2.dist-info/top_level.txt
pmenu_lib-1.2.2.dist-info/RECORD
