Metadata-Version: 2.4
Name: pmenu-lib
Version: 1.2.2
Summary: Sleek dmenu alternative written in Python and powered by curses.
Author-email: Julio Cabria <juliocabria@tutanota.com>
Maintainer-email: Julio Cabria <juliocabria@tutanota.com>
License: GPLv2
Project-URL: Homepage, https://github.com/Julynx/pmenu
Project-URL: Repository, https://github.com/Julynx/pmenu
Project-URL: Issues, https://github.com/Julynx/pmenu/issues
Keywords: dmenu,menu,terminal,curses,cli
Classifier: Development Status :: 5 - Production/Stable
Classifier: Environment :: Console :: Curses
Classifier: Intended Audience :: Developers
Classifier: License :: OSI Approved :: GNU General Public License v2 (GPLv2)
Classifier: Operating System :: OS Independent
Classifier: Programming Language :: Python :: 3
Classifier: Programming Language :: Python :: 3.7
Classifier: Programming Language :: Python :: 3.8
Classifier: Programming Language :: Python :: 3.9
Classifier: Programming Language :: Python :: 3.10
Classifier: Programming Language :: Python :: 3.11
Classifier: Programming Language :: Python :: 3.12
Classifier: Programming Language :: Python :: 3.13
Classifier: Topic :: Software Development :: Libraries :: Python Modules
Classifier: Topic :: Terminals
Requires-Python: >=3.8
License-File: LICENSE
Requires-Dist: windows-curses>=2.3.0; platform_system == "Windows"
Dynamic: license-file
